ggxs/__init__.py
ggxs/ggxs.py
ggxs/account/__init__.py
ggxs/account/account.py
ggxs/account/auth.py
ggxs/alliance/__init__.py
ggxs/alliance/alliance.py
ggxs/army/__init__.py
ggxs/army/lords.py
ggxs/building/__init__.py
ggxs/building/build_items.py
ggxs/building/buildings.py
ggxs/building/buildings_inventory.py
ggxs/building/extension.py
ggxs/building/repair.py
ggxs/building/wall.py
ggxs/castle/__init__.py
ggxs/castle/castle.py
ggxs/castle/defense.py
ggxs/client/__init__.py
ggxs/client/_cfg.py
ggxs/client/game_client.py
ggxs/client/memcache.py
ggxs/client/planner.py
ggxs/client/server_loader.py
ggxs/equip/__init__.py
ggxs/equip/equip.py
ggxs/events/__init__.py
ggxs/events/affluence_wheel.py
ggxs/events/beyond_the_horizon.py
ggxs/events/events.py
ggxs/events/grand_tournament.py
ggxs/events/imperial_patronage.py
ggxs/events/outer_realms.py
ggxs/map/__init__.py
ggxs/map/attack.py
ggxs/map/bookmarks.py
ggxs/map/map.py
ggxs/map/movements.py
ggxs/map/spy.py
ggxs/map/support.py
ggxs/misc/__init__.py
ggxs/misc/gifts.py
ggxs/misc/global_effects.py
ggxs/misc/misc.py
ggxs/misc/quests.py
ggxs/misc/tax.py
ggxs/misc/tutorial.py
ggxs/presets/__init__.py
ggxs/presets/presets.py
ggxs/production/__init__.py
ggxs/production/hospital.py
ggxs/production/refinery.py
ggxs/production/soldiers.py
ggxs/production/tools.py
ggxs/shops/__init__.py
ggxs/shops/bestseller.py
ggxs/shops/kings_market.py
ggxs/shops/shop.py
ggxs/social/__init__.py
ggxs/social/social.py
ggxs/utils/__init__.py
ggxs/utils/utils.py
ggxs-1.1b0.dist-info/licenses/LICENSE
ggxs-1.1b0.dist-info/METADATA
ggxs-1.1b0.dist-info/WHEEL
ggxs-1.1b0.dist-info/top_level.txt
ggxs-1.1b0.dist-info/RECORD
