Metadata-Version: 2.4
Name: ggxs
Version: 1.1b0
Summary: GoodGame Empire websocket engine.
Author-email: mst4ck <mst4ck@mailfence.com>
License: MIT
Classifier: Programming Language :: Python :: 3
Classifier: Operating System :: OS Independent
Requires-Python: >=3.12
License-File: LICENSE
Requires-Dist: websockets>=15.0.1
Requires-Dist: loguru>=0.7.3
Requires-Dist: aiohttp>=3.13.0
Dynamic: license-file
